{"user": "thamiris", "salvo_em": "2026-06-24T17:18:24.175577", "itens": [{"fornecedor": "—", "produto_id": "67274590", "produto_nome": "Fone Bluetooth Smart Touch Kaidi", "cod_interno": "KD-7019", "variacao_id": "113757885", "variacao_cod": "KD-7019", "variacao_nome": "(sem nome)", "estoque_atual": -24, "quantidade": 5, "valor_custo": "70.00"}, {"fornecedor": "—", "produto_id": "74875549", "produto_nome": "Fone Bluetooth KD-780 Kaidi", "cod_interno": "KD-780", "variacao_id": "127230397", "variacao_cod": "KD-7800001", "variacao_nome": "Preto", "estoque_atual": -24, "quantidade": 10, "valor_custo": "28.00"}, {"fornecedor": "—", "produto_id": "56160217", "produto_nome": "Fone auricular com fio Hi Turbo", "cod_interno": "T-666", "variacao_id": "95101319", "variacao_cod": "T-6660001", "variacao_nome": "Preto", "estoque_atual": -18, "quantidade": 5, "valor_custo": "14.50"}, {"fornecedor": "—", "produto_id": "56160217", "produto_nome": "Fone auricular com fio Hi Turbo", "cod_interno": "T-666", "variacao_id": "95101320", "variacao_cod": "T-6660002", "variacao_nome": "Branco", "estoque_atual": -6, "quantidade": 5, "valor_custo": "14.50"}, {"fornecedor": "—", "produto_id": "69873251", "produto_nome": "MagSafe Powerbank 5000mAh Kaidi", "cod_interno": "KNC8885", "variacao_id": "118294565", "variacao_cod": "KNC88850001", "variacao_nome": "Branco", "estoque_atual": -16, "quantidade": 5, "valor_custo": "70.00"}, {"fornecedor": "—", "produto_id": "69873251", "produto_nome": "MagSafe Powerbank 5000mAh Kaidi", "cod_interno": "KNC8885", "variacao_id": "118294566", "variacao_cod": "KNC88850002", "variacao_nome": "Preto", "estoque_atual": -22, "quantidade": 5, "valor_custo": "70.00"}, {"fornecedor": "—", "produto_id": "78557407", "produto_nome": "Cabo Liga de Borracha It Blue Tipo V8", "cod_interno": "LE-849V", "variacao_id": "133765809", "variacao_cod": "LE-849V", "variacao_nome": "(sem nome)", "estoque_atual": -22, "quantidade": 10, "valor_custo": "13.00"}, {"fornecedor": "—", "produto_id": "92351289", "produto_nome": "Cabo Liga de Borracha A'GOLD  iOS", "cod_interno": "CB129-2", "variacao_id": "161066794", "variacao_cod": "CB129-2", "variacao_nome": "(sem nome)", "estoque_atual": -17, "quantidade": 20, "valor_custo": "13.00"}, {"fornecedor": "—", "produto_id": "73495492", "produto_nome": "Cabo Liga de Borracha It Blue Tipo C", "cod_interno": "LE-849C", "variacao_id": "124736157", "variacao_cod": "LE-849C", "variacao_nome": "(sem nome)", "estoque_atual": -35, "quantidade": 10, "valor_custo": "13.00"}, {"fornecedor": "—", "produto_id": "56599879", "produto_nome": "Hidrogel", "cod_interno": "Hidrogel", "variacao_id": "95780951", "variacao_cod": "Hidrogel0001", "variacao_nome": "Clara", "estoque_atual": -1406, "quantidade": 50, "valor_custo": "0.00"}, {"fornecedor": "—", "produto_id": "56599879", "produto_nome": "Hidrogel", "cod_interno": "Hidrogel", "variacao_id": "95780953", "variacao_cod": "Hidrogel0003", "variacao_nome": "Fosca Privacidade", "estoque_atual": -483, "quantidade": 50, "valor_custo": "0.00"}, {"fornecedor": "—", "produto_id": "56599879", "produto_nome": "Hidrogel", "cod_interno": "Hidrogel", "variacao_id": "115783862", "variacao_cod": "Hidrogel0005", "variacao_nome": "Lisa Privacidade", "estoque_atual": -255, "quantidade": 50, "valor_custo": "0.00"}], "avulsos": [], "fornecedor": "", "obs": "", "data": "2026-06-24"}